GitHubRecommender/__init__.py
GitHubRecommender/data_acquisition.py
GitHubRecommender/data_processing.py
GitHubRecommender/fetch_repos.py
GitHubRecommender/main.py
GitHubRecommender/news_acquisition.py
GitHubRecommender/recommender_system.py
GitHubRecommender/tests/__init__.py
GitHubRecommender/tests/test_data_acquisition.py
GitHubRecommender/tests/test_data_processing.py
GitHubRecommender-0.1.dist-info/LICENSE
GitHubRecommender-0.1.dist-info/METADATA
GitHubRecommender-0.1.dist-info/WHEEL
GitHubRecommender-0.1.dist-info/top_level.txt
GitHubRecommender-0.1.dist-info/RECORD
